ulibpy
